<?xml version="1.0" encoding="UTF-8"?>
<GenRun Id="synth_1" LaunchPart="xc7a100tcsg324-1" LaunchTime="1716370944">
  <File Type="VDS-TIMING-PB" Name="router_mesh_top_timing_summary_synth.pb"/>
  <File Type="VDS-TIMINGSUMMARY" Name="router_mesh_top_timing_summary_synth.rpt"/>
  <File Type="RDS-DCP" Name="router_mesh_top.dcp"/>
  <File Type="RDS-UTIL-PB" Name="router_mesh_top_utilization_synth.pb"/>
  <File Type="RDS-UTIL" Name="router_mesh_top_utilization_synth.rpt"/>
  <File Type="RDS-PROPCONSTRS" Name="router_mesh_top_drc_synth.rpt"/>
  <File Type="RDS-RDS" Name="router_mesh_top.vds"/>
  <File Type="REPORTS-TCL" Name="router_mesh_top_reports.tcl"/>
  <File Type="PA-TCL" Name="router_mesh_top.tcl"/>
  <FileSet Name="sources" Type="DesignSrcs" RelSrcDir="$PSRCDIR/sources_1" RelGenDir="$PGENDIR/sources_1">
    <Filter Type="Srcs"/>
    <File Path="$PSRCDIR/sources_1/imports/misc/defs.vhd">
      <FileInfo>
        <Attr Name="ImportPath" Val="$PPRDIR/../../Async-Click-Library/src/misc/defs.vhd"/>
        <Attr Name="ImportTime" Val="1710163939"/>
        <Attr Name="UsedIn" Val="synthesis"/>
        <Attr Name="UsedIn" Val="simulation"/>
      </FileInfo>
    </File>
    <File Path="$PSRCDIR/sources_1/imports/components/DEMUX.vhd">
      <FileInfo>
        <Attr Name="ImportPath" Val="$PPRDIR/../../Async-Click-Library/src/components/DEMUX.vhd"/>
        <Attr Name="ImportTime" Val="1710163939"/>
        <Attr Name="UsedIn" Val="synthesis"/>
        <Attr Name="UsedIn" Val="simulation"/>
      </FileInfo>
    </File>
    <File Path="$PSRCDIR/sources_1/imports/components/rgd_mutex.vhd">
      <FileInfo>
        <Attr Name="ImportPath" Val="$PPRDIR/../../Async-Click-Library/src/components/rgd_mutex.vhd"/>
        <Attr Name="ImportTime" Val="1710163939"/>
        <Attr Name="UsedIn" Val="synthesis"/>
        <Attr Name="UsedIn" Val="simulation"/>
      </FileInfo>
    </File>
    <File Path="$PSRCDIR/sources_1/imports/components/merge.vhd">
      <FileInfo>
        <Attr Name="ImportPath" Val="$PPRDIR/../../Async-Click-Library/src/components/merge.vhd"/>
        <Attr Name="ImportTime" Val="1710163939"/>
        <Attr Name="UsedIn" Val="synthesis"/>
        <Attr Name="UsedIn" Val="simulation"/>
      </FileInfo>
    </File>
    <File Path="$PSRCDIR/sources_1/imports/components/arbiter.vhd">
      <FileInfo>
        <Attr Name="ImportPath" Val="$PPRDIR/../../Async-Click-Library/src/components/arbiter.vhd"/>
        <Attr Name="ImportTime" Val="1710163939"/>
        <Attr Name="UsedIn" Val="synthesis"/>
        <Attr Name="UsedIn" Val="simulation"/>
      </FileInfo>
    </File>
    <File Path="$PSRCDIR/sources_1/imports/components/click_element.vhd">
      <FileInfo>
        <Attr Name="ImportPath" Val="$PPRDIR/../../Async-Click-Library/src/components/click_element.vhd"/>
        <Attr Name="ImportTime" Val="1710163939"/>
        <Attr Name="UsedIn" Val="synthesis"/>
        <Attr Name="UsedIn" Val="simulation"/>
      </FileInfo>
    </File>
    <File Path="$PSRCDIR/sources_1/new/arbiter3.vhd">
      <FileInfo>
        <Attr Name="UsedIn" Val="synthesis"/>
        <Attr Name="UsedIn" Val="simulation"/>
      </FileInfo>
    </File>
    <File Path="$PSRCDIR/sources_1/new/arbiter5.vhd">
      <FileInfo>
        <Attr Name="UsedIn" Val="synthesis"/>
        <Attr Name="UsedIn" Val="simulation"/>
      </FileInfo>
    </File>
    <File Path="$PSRCDIR/sources_1/new/demux3.vhd">
      <FileInfo>
        <Attr Name="UsedIn" Val="synthesis"/>
        <Attr Name="UsedIn" Val="simulation"/>
      </FileInfo>
    </File>
    <File Path="$PSRCDIR/sources_1/new/router.vhd">
      <FileInfo>
        <Attr Name="UsedIn" Val="synthesis"/>
        <Attr Name="UsedIn" Val="simulation"/>
      </FileInfo>
    </File>
    <File Path="$PSRCDIR/sources_1/new/corner_node_top.vhd">
      <FileInfo>
        <Attr Name="UsedIn" Val="synthesis"/>
        <Attr Name="UsedIn" Val="simulation"/>
      </FileInfo>
    </File>
    <File Path="$PSRCDIR/sources_1/new/demux5.vhd">
      <FileInfo>
        <Attr Name="UsedIn" Val="synthesis"/>
        <Attr Name="UsedIn" Val="simulation"/>
      </FileInfo>
    </File>
    <File Path="$PSRCDIR/sources_1/new/router_node_top.vhd">
      <FileInfo>
        <Attr Name="UsedIn" Val="synthesis"/>
        <Attr Name="UsedIn" Val="simulation"/>
      </FileInfo>
    </File>
    <File Path="$PSRCDIR/sources_1/new/router5.vhd">
      <FileInfo>
        <Attr Name="UsedIn" Val="synthesis"/>
        <Attr Name="UsedIn" Val="simulation"/>
      </FileInfo>
    </File>
    <File Path="$PSRCDIR/sources_1/new/router2.vhd">
      <FileInfo>
        <Attr Name="UsedIn" Val="synthesis"/>
        <Attr Name="UsedIn" Val="simulation"/>
      </FileInfo>
    </File>
    <File Path="$PSRCDIR/sources_1/new/side_node_top.vhd">
      <FileInfo>
        <Attr Name="UsedIn" Val="synthesis"/>
        <Attr Name="UsedIn" Val="simulation"/>
      </FileInfo>
    </File>
    <File Path="$PSRCDIR/sources_1/new/router_mesh_top.vhd">
      <FileInfo>
        <Attr Name="UsedIn" Val="synthesis"/>
        <Attr Name="UsedIn" Val="simulation"/>
      </FileInfo>
    </File>
    <File Path="$PSRCDIR/sources_1/new/generator.vhd">
      <FileInfo>
        <Attr Name="AutoDisabled" Val="1"/>
        <Attr Name="UsedIn" Val="synthesis"/>
        <Attr Name="UsedIn" Val="simulation"/>
      </FileInfo>
    </File>
    <File Path="$PSRCDIR/sources_1/imports/components/reg_demux.vhdl">
      <FileInfo>
        <Attr Name="AutoDisabled" Val="1"/>
        <Attr Name="ImportPath" Val="$PPRDIR/../../Async-Click-Library/src/components/reg_demux.vhdl"/>
        <Attr Name="ImportTime" Val="1710163939"/>
        <Attr Name="UsedIn" Val="synthesis"/>
        <Attr Name="UsedIn" Val="simulation"/>
      </FileInfo>
    </File>
    <File Path="$PSRCDIR/sources_1/imports/examples/Fib_top.vhd">
      <FileInfo>
        <Attr Name="AutoDisabled" Val="1"/>
        <Attr Name="ImportPath" Val="$PPRDIR/../../Async-Click-Library/src/examples/Fib_top.vhd"/>
        <Attr Name="ImportTime" Val="1710163939"/>
        <Attr Name="UsedIn" Val="synthesis"/>
        <Attr Name="UsedIn" Val="simulation"/>
      </FileInfo>
    </File>
    <File Path="$PSRCDIR/sources_1/imports/components/MUX.vhd">
      <FileInfo>
        <Attr Name="AutoDisabled" Val="1"/>
        <Attr Name="ImportPath" Val="$PPRDIR/../../Async-Click-Library/src/components/MUX.vhd"/>
        <Attr Name="ImportTime" Val="1710163939"/>
        <Attr Name="UsedIn" Val="synthesis"/>
        <Attr Name="UsedIn" Val="simulation"/>
      </FileInfo>
    </File>
    <File Path="$PSRCDIR/sources_1/imports/components/barrier.vhd">
      <FileInfo>
        <Attr Name="AutoDisabled" Val="1"/>
        <Attr Name="ImportPath" Val="$PPRDIR/../../Async-Click-Library/src/components/barrier.vhd"/>
        <Attr Name="ImportTime" Val="1710163939"/>
        <Attr Name="UsedIn" Val="synthesis"/>
        <Attr Name="UsedIn" Val="simulation"/>
      </FileInfo>
    </File>
    <File Path="$PSRCDIR/sources_1/imports/components/decoup_hs.vhd">
      <FileInfo>
        <Attr Name="AutoDisabled" Val="1"/>
        <Attr Name="ImportPath" Val="$PPRDIR/../../Async-Click-Library/src/components/decoup_hs.vhd"/>
        <Attr Name="ImportTime" Val="1710163939"/>
        <Attr Name="UsedIn" Val="synthesis"/>
        <Attr Name="UsedIn" Val="simulation"/>
      </FileInfo>
    </File>
    <File Path="$PSRCDIR/sources_1/imports/components/delay_element.vhd">
      <FileInfo>
        <Attr Name="AutoDisabled" Val="1"/>
        <Attr Name="ImportPath" Val="$PPRDIR/../../Async-Click-Library/src/components/delay_element.vhd"/>
        <Attr Name="ImportTime" Val="1710163939"/>
        <Attr Name="UsedIn" Val="synthesis"/>
        <Attr Name="UsedIn" Val="simulation"/>
      </FileInfo>
    </File>
    <File Path="$PSRCDIR/sources_1/imports/components/join.vhd">
      <FileInfo>
        <Attr Name="AutoDisabled" Val="1"/>
        <Attr Name="ImportPath" Val="$PPRDIR/../../Async-Click-Library/src/components/join.vhd"/>
        <Attr Name="ImportTime" Val="1710163939"/>
        <Attr Name="UsedIn" Val="synthesis"/>
        <Attr Name="UsedIn" Val="simulation"/>
      </FileInfo>
    </File>
    <File Path="$PSRCDIR/sources_1/imports/components/reg_fork.vhd">
      <FileInfo>
        <Attr Name="AutoDisabled" Val="1"/>
        <Attr Name="ImportPath" Val="$PPRDIR/../../Async-Click-Library/src/components/reg_fork.vhd"/>
        <Attr Name="ImportTime" Val="1710163939"/>
        <Attr Name="UsedIn" Val="synthesis"/>
        <Attr Name="UsedIn" Val="simulation"/>
      </FileInfo>
    </File>
    <File Path="$PSRCDIR/sources_1/imports/examples/fibonacci.vhd">
      <FileInfo>
        <Attr Name="AutoDisabled" Val="1"/>
        <Attr Name="ImportPath" Val="$PPRDIR/../../Async-Click-Library/src/examples/fibonacci.vhd"/>
        <Attr Name="ImportTime" Val="1710163939"/>
        <Attr Name="UsedIn" Val="synthesis"/>
        <Attr Name="UsedIn" Val="simulation"/>
      </FileInfo>
    </File>
    <File Path="$PSRCDIR/sources_1/imports/components/fork.vhd">
      <FileInfo>
        <Attr Name="AutoDisabled" Val="1"/>
        <Attr Name="ImportPath" Val="$PPRDIR/../../Async-Click-Library/src/components/fork.vhd"/>
        <Attr Name="ImportTime" Val="1710163939"/>
        <Attr Name="UsedIn" Val="synthesis"/>
        <Attr Name="UsedIn" Val="simulation"/>
      </FileInfo>
    </File>
    <File Path="$PSRCDIR/sources_1/imports/components/join_reg_fork.vhd">
      <FileInfo>
        <Attr Name="AutoDisabled" Val="1"/>
        <Attr Name="ImportPath" Val="$PPRDIR/../../Async-Click-Library/src/components/join_reg_fork.vhd"/>
        <Attr Name="ImportTime" Val="1710163939"/>
        <Attr Name="UsedIn" Val="synthesis"/>
        <Attr Name="UsedIn" Val="simulation"/>
      </FileInfo>
    </File>
    <File Path="$PSRCDIR/sources_1/imports/components/reg_merge.vhd">
      <FileInfo>
        <Attr Name="AutoDisabled" Val="1"/>
        <Attr Name="ImportPath" Val="$PPRDIR/../../Async-Click-Library/src/components/reg_merge.vhd"/>
        <Attr Name="ImportTime" Val="1710163939"/>
        <Attr Name="UsedIn" Val="synthesis"/>
        <Attr Name="UsedIn" Val="simulation"/>
      </FileInfo>
    </File>
    <File Path="$PSRCDIR/sources_1/imports/components/reg_mux.vhd">
      <FileInfo>
        <Attr Name="AutoDisabled" Val="1"/>
        <Attr Name="ImportPath" Val="$PPRDIR/../../Async-Click-Library/src/components/reg_mux.vhd"/>
        <Attr Name="ImportTime" Val="1710163939"/>
        <Attr Name="UsedIn" Val="synthesis"/>
        <Attr Name="UsedIn" Val="simulation"/>
      </FileInfo>
    </File>
    <Config>
      <Option Name="DesignMode" Val="RTL"/>
      <Option Name="TopModule" Val="router_mesh_top"/>
    </Config>
  </FileSet>
  <FileSet Name="constrs_in" Type="Constrs" RelSrcDir="$PSRCDIR/constrs_1" RelGenDir="$PGENDIR/constrs_1">
    <Filter Type="Constrs"/>
    <Config>
      <Option Name="ConstrsType" Val="XDC"/>
    </Config>
  </FileSet>
  <FileSet Name="utils" Type="Utils" RelSrcDir="$PSRCDIR/utils_1" RelGenDir="$PGENDIR/utils_1">
    <Filter Type="Utils"/>
    <Config>
      <Option Name="TopAutoSet" Val="TRUE"/>
    </Config>
  </FileSet>
  <Strategy Version="1" Minor="2">
    <StratHandle Name="Vivado Synthesis Defaults" Flow="Vivado Synthesis 2023"/>
    <Step Id="synth_design"/>
  </Strategy>
</GenRun>
